{
  "project_info": {
    "project_number": "940727465385",
    "project_id": "notifica-36352",
    "storage_bucket": "notifica-36352.appspot.com"
  },
  "client": [
    {
      "client_info": {
        "mobilesdk_app_id": "1:940727465385:android:80cca159f15a018dbd80b8",
        "android_client_info": {
          "package_name": "com.notifica"
        }
      },
      "oauth_client": [
        {
          "client_id": "940727465385-sd2r3uljs3mc634qbipnb3s2qrtp26r3.apps.googleusercontent.com",
          "client_type": 3
        }
      ],
      "api_key": [
        {
          "current_key": "AIzaSyCruO2FssOLddBgl-nV2WCTdQUUSolVIbY"
        }
      ],
      "services": {
        "appinvite_service": {
          "other_platform_oauth_client": [
            {
              "client_id": "940727465385-sd2r3uljs3mc634qbipnb3s2qrtp26r3.apps.googleusercontent.com",
              "client_type": 3
            }
          ]
        }
      }
    }
  ],
  "configuration_version": "1"
}